gp.recipe.tox-0.4-py2.7-nspkg.pth
gp.recipe.tox-0.4.dist-info/namespace_packages.txt
gp.recipe.tox-0.4.dist-info/top_level.txt
gp.recipe.tox-0.4.dist-info/DESCRIPTION.rst
gp.recipe.tox-0.4.dist-info/METADATA
gp.recipe.tox-0.4.dist-info/entry_points.txt
gp.recipe.tox-0.4.dist-info/RECORD
gp.recipe.tox-0.4.dist-info/metadata.json
gp.recipe.tox-0.4.dist-info/WHEEL
gp/recipe/tox/README.txt
gp/recipe/tox/__init__.py
