Metadata-Version: 2.0
Name: gp.recipe.tox
Version: 0.4
Summary: use buildout with tox
Home-page: https://github.com/gawel/gp.recipe.tox
Author: Gael Pasgrimaud
Author-email: gael@gawel.org
License: gpl
Keywords: tox buildout
Platform: UNKNOWN
Classifier: Framework :: Buildout
Classifier: Intended Audience :: Developers
Classifier: Topic :: Software Development :: Build Tools
Requires-Dist: setuptools
Requires-Dist: zc.buildout
Requires-Dist: zc.recipe.egg
Requires-Dist: virtualenv
Provides-Extra: tests
Requires-Dist: zope.testing; extra == 'tests'
Requires-Dist: zc.buildout; extra == 'tests'
